scrapyd_api/__init__.py
scrapyd_api/constants.py
scrapyd_api/exceptions.py
scrapyd_api/scrapyd_api.py
scrapyd_api/scrapyd_client.py
scrapyd_api/version.py
scrapyd_api-0.0.4.dist-info/METADATA
scrapyd_api-0.0.4.dist-info/WHEEL
scrapyd_api-0.0.4.dist-info/top_level.txt
scrapyd_api-0.0.4.dist-info/zip-safe
scrapyd_api-0.0.4.dist-info/RECORD
