Metadata-Version: 2.1
Name: scrapyd-api
Version: 0.0.4
Summary: scrapyd api
Home-page: https://github.com/mouday/scrapyd-api
Author: Peng Shiyu
Author-email: pengshiyuyx@gmail.com
License: MIT
Keywords: spider admin
Classifier: Programming Language :: Python :: 3
Classifier: Programming Language :: Python :: 3.6
Requires-Dist: parsel
Requires-Dist: session-request
